tornadobase/__init__.py
tornadobase/application.py
tornadobase/config.py
tornadobase/handlers/__init__.py
tornadobase/handlers/basehandler.py
tornadobase/tests/__init__.py
tornadobase/tests/test_application.py
tornadobase-0.1.7.dist-info/DESCRIPTION.rst
tornadobase-0.1.7.dist-info/METADATA
tornadobase-0.1.7.dist-info/RECORD
tornadobase-0.1.7.dist-info/WHEEL
tornadobase-0.1.7.dist-info/metadata.json
tornadobase-0.1.7.dist-info/top_level.txt
