Metadata-Version: 2.0
Name: tornadobase
Version: 0.1.7
Summary: Starter application and handlers for tornado web apps.
Home-page: https://github.com/coyote240/tornadobase
Author: Adam A.G. Shamblin
Author-email: adam.shamblin@tutanota.com
License: MIT
Platform: UNKNOWN
Requires-Dist: tornado (>=4)
